Metadata-Version: 2.1
Name: curly-potato
Version: 0.1.2
Summary: An example Python package
Home-page: https://github.com/UnrealEugene/curly_potato
Author: Eugene Chernatskiy
Author-email: chernatskiy2001@gmail.com
License: BSD 2-clause
Platform: UNKNOWN
Classifier: Development Status :: 1 - Planning
Classifier: Intended Audience :: Science/Research
Classifier: License :: OSI Approved :: BSD License
Classifier: Operating System :: POSIX :: Linux
Classifier: Programming Language :: Python :: 2
Classifier: Programming Language :: Python :: 2.7
Classifier: Programming Language :: Python :: 3
Classifier: Programming Language :: Python :: 3.4
Classifier: Programming Language :: Python :: 3.5
License-File: LICENSE
